{
    "仿真结果": [
        {
            "headings": [
                "元件名称",
                "设备型号",
                "设备台数",
                "产冷量（kWh）",
                "冷负荷（kWh）",
                "产热量（kWh）",
                "冷热荷（kWh）",
                "产电量（kWh）",
                "电负荷（kWh）",
                "蒸汽产量（t）",
                "蒸汽负荷（t）",
                "氢气产量（Nm³）",
                "氢气消耗量（Nm³）",
                "柴油消耗量（L）",
                "柴油消耗费用（万元）",
                "天然气消耗量（Nm³）",
                "天然气消耗费用（万元）",
                "平均效率/平均COP",
                "设备维护费用（万元）",
                "冷收入（万元）",
                "热收入（万元）",
                "电收入（万元）",
                "蒸汽收入（万元）",
                "氢气收入（万元）"
            ],
            "devices": []
        }
    ],
    "设备出力曲线": [
        {
            "headings": [
                "元件名称",
                "时间",
                "发电功率（kW）"
            ],
            "devices": [
                "光伏发电",
                "风力发电",
                "柴油发电"
            ]
        },
        {
            "headings": [
                "元件名称",
                "时间",
                "充电功率（kW）",
                "放电功率（kW）",
                "荷电容量（kWh）",
                "荷电状态（%)"
            ],
            "devices": [
                "锂电池"
            ]
        },
        {
            "headings": [
                "元件名称",
                "时间",
                "转换功率（kW）"
            ],
            "devices": [
                "变压器",
                "变流器",
                "双向变流器"
            ]
        }
    ]
}